gitlab_settings_manager/__init__.py
gitlab_settings_manager/gitlab_add_reviewers.py
gitlab_settings_manager/gitlab_settings_manager.py
gitlab_settings_manager-0.1.20230123233844.dist-info/METADATA
gitlab_settings_manager-0.1.20230123233844.dist-info/WHEEL
gitlab_settings_manager-0.1.20230123233844.dist-info/entry_points.txt
gitlab_settings_manager-0.1.20230123233844.dist-info/top_level.txt
gitlab_settings_manager-0.1.20230123233844.dist-info/RECORD
